{
  "id": "da1554c9-153e-469a-a9be-6a381050389a",
  "prevId": "00000000-0000-0000-0000-000000000000",
  "version": "7",
  "dialect": "postgresql",
  "tables": {
    "public.bouts": {
      "name": "bouts",
      "schema": "",
      "columns": {
        "id": {
          "name": "id",
          "type": "text",
          "primaryKey": true,
          "notNull": true,
          "default": "'gen_random_uuid()'"
        },
        "event_id": {
          "name": "event_id",
          "type": "text",
          "primaryKey": false,
          "notNull": true
        },
        "fighter_a_id": {
          "name": "fighter_a_id",
          "type": "text",
          "primaryKey": false,
          "notNull": true
        },
        "fighter_b_id": {
          "name": "fighter_b_id",
          "type": "text",
          "primaryKey": false,
          "notNull": true
        },
        "weight_class": {
          "name": "weight_class",
          "type": "weight_class",
          "typeSchema": "public",
          "primaryKey": false,
          "notNull": true
        },
        "is_title_fight": {
          "name": "is_title_fight",
          "type": "boolean",
          "primaryKey": false,
          "notNull": true,
          "default": false
        },
        "is_main_event": {
          "name": "is_main_event",
          "type": "boolean",
          "primaryKey": false,
          "notNull": true,
          "default": false
        },
        "card_segment": {
          "name": "card_segment",
          "type": "card_segment",
          "typeSchema": "public",
          "primaryKey": false,
          "notNull": true,
          "default": "'prelim'"
        },
        "bout_order": {
          "name": "bout_order",
          "type": "integer",
          "primaryKey": false,
          "notNull": true,
          "default": 0
        },
        "scheduled_start": {
          "name": "scheduled_start",
          "type": "timestamp with time zone",
          "primaryKey": false,
          "notNull": false
        },
        "status": {
          "name": "status",
          "type": "bout_status",
          "typeSchema": "public",
          "primaryKey": false,
          "notNull": true,
          "default": "'scheduled'"
        },
        "winner_id": {
          "name": "winner_id",
          "type": "text",
          "primaryKey": false,
          "notNull": false
        },
        "method": {
          "name": "method",
          "type": "bout_method",
          "typeSchema": "public",
          "primaryKey": false,
          "notNull": false
        },
        "is_finish": {
          "name": "is_finish",
          "type": "boolean",
          "primaryKey": false,
          "notNull": true,
          "default": false
        },
        "end_round": {
          "name": "end_round",
          "type": "integer",
          "primaryKey": false,
          "notNull": false
        },
        "fighter_a_ranked": {
          "name": "fighter_a_ranked",
          "type": "boolean",
          "primaryKey": false,
          "notNull": true,
          "default": false
        },
        "fighter_b_ranked": {
          "name": "fighter_b_ranked",
          "type": "boolean",
          "primaryKey": false,
          "notNull": true,
          "default": false
        },
        "fotn": {
          "name": "fotn",
          "type": "boolean",
          "primaryKey": false,
          "notNull": true,
          "default": false
        },
        "fighter_a_potn": {
          "name": "fighter_a_potn",
          "type": "boolean",
          "primaryKey": false,
          "notNull": true,
          "default": false
        },
        "fighter_b_potn": {
          "name": "fighter_b_potn",
          "type": "boolean",
          "primaryKey": false,
          "notNull": true,
          "default": false
        }
      },
      "indexes": {},
      "foreignKeys": {
        "bouts_event_id_events_id_fk": {
          "name": "bouts_event_id_events_id_fk",
          "tableFrom": "bouts",
          "tableTo": "events",
          "columnsFrom": [
            "event_id"
          ],
          "columnsTo": [
            "id"
          ],
          "onDelete": "no action",
          "onUpdate": "no action"
        },
        "bouts_fighter_a_id_fighters_id_fk": {
          "name": "bouts_fighter_a_id_fighters_id_fk",
          "tableFrom": "bouts",
          "tableTo": "fighters",
          "columnsFrom": [
            "fighter_a_id"
          ],
          "columnsTo": [
            "id"
          ],
          "onDelete": "no action",
          "onUpdate": "no action"
        },
        "bouts_fighter_b_id_fighters_id_fk": {
          "name": "bouts_fighter_b_id_fighters_id_fk",
          "tableFrom": "bouts",
          "tableTo": "fighters",
          "columnsFrom": [
            "fighter_b_id"
          ],
          "columnsTo": [
            "id"
          ],
          "onDelete": "no action",
          "onUpdate": "no action"
        },
        "bouts_winner_id_fighters_id_fk": {
          "name": "bouts_winner_id_fighters_id_fk",
          "tableFrom": "bouts",
          "tableTo": "fighters",
          "columnsFrom": [
            "winner_id"
          ],
          "columnsTo": [
            "id"
          ],
          "onDelete": "no action",
          "onUpdate": "no action"
        }
      },
      "compositePrimaryKeys": {},
      "uniqueConstraints": {},
      "policies": {},
      "checkConstraints": {},
      "isRLSEnabled": false
    },
    "public.draft_picks": {
      "name": "draft_picks",
      "schema": "",
      "columns": {
        "id": {
          "name": "id",
          "type": "text",
          "primaryKey": true,
          "notNull": true,
          "default": "'gen_random_uuid()'"
        },
        "draft_id": {
          "name": "draft_id",
          "type": "text",
          "primaryKey": false,
          "notNull": true
        },
        "pick_number": {
          "name": "pick_number",
          "type": "integer",
          "primaryKey": false,
          "notNull": true
        },
        "round": {
          "name": "round",
          "type": "integer",
          "primaryKey": false,
          "notNull": true
        },
        "membership_id": {
          "name": "membership_id",
          "type": "text",
          "primaryKey": false,
          "notNull": true
        },
        "fighter_id": {
          "name": "fighter_id",
          "type": "text",
          "primaryKey": false,
          "notNull": false
        },
        "slot": {
          "name": "slot",
          "type": "slot",
          "typeSchema": "public",
          "primaryKey": false,
          "notNull": false
        },
        "picked_at": {
          "name": "picked_at",
          "type": "timestamp with time zone",
          "primaryKey": false,
          "notNull": false
        },
        "is_autopick": {
          "name": "is_autopick",
          "type": "boolean",
          "primaryKey": false,
          "notNull": true,
          "default": false
        }
      },
      "indexes": {},
      "foreignKeys": {
        "draft_picks_draft_id_drafts_id_fk": {
          "name": "draft_picks_draft_id_drafts_id_fk",
          "tableFrom": "draft_picks",
          "tableTo": "drafts",
          "columnsFrom": [
            "draft_id"
          ],
          "columnsTo": [
            "id"
          ],
          "onDelete": "no action",
          "onUpdate": "no action"
        },
        "draft_picks_membership_id_league_memberships_id_fk": {
          "name": "draft_picks_membership_id_league_memberships_id_fk",
          "tableFrom": "draft_picks",
          "tableTo": "league_memberships",
          "columnsFrom": [
            "membership_id"
          ],
          "columnsTo": [
            "id"
          ],
          "onDelete": "no action",
          "onUpdate": "no action"
        },
        "draft_picks_fighter_id_fighters_id_fk": {
          "name": "draft_picks_fighter_id_fighters_id_fk",
          "tableFrom": "draft_picks",
          "tableTo": "fighters",
          "columnsFrom": [
            "fighter_id"
          ],
          "columnsTo": [
            "id"
          ],
          "onDelete": "no action",
          "onUpdate": "no action"
        }
      },
      "compositePrimaryKeys": {},
      "uniqueConstraints": {},
      "policies": {},
      "checkConstraints": {},
      "isRLSEnabled": false
    },
    "public.draft_queues": {
      "name": "draft_queues",
      "schema": "",
      "columns": {
        "id": {
          "name": "id",
          "type": "text",
          "primaryKey": true,
          "notNull": true,
          "default": "'gen_random_uuid()'"
        },
        "membership_id": {
          "name": "membership_id",
          "type": "text",
          "primaryKey": false,
          "notNull": true
        },
        "fighter_id": {
          "name": "fighter_id",
          "type": "text",
          "primaryKey": false,
          "notNull": true
        },
        "priority": {
          "name": "priority",
          "type": "integer",
          "primaryKey": false,
          "notNull": true
        }
      },
      "indexes": {},
      "foreignKeys": {
        "draft_queues_membership_id_league_memberships_id_fk": {
          "name": "draft_queues_membership_id_league_memberships_id_fk",
          "tableFrom": "draft_queues",
          "tableTo": "league_memberships",
          "columnsFrom": [
            "membership_id"
          ],
          "columnsTo": [
            "id"
          ],
          "onDelete": "no action",
          "onUpdate": "no action"
        },
        "draft_queues_fighter_id_fighters_id_fk": {
          "name": "draft_queues_fighter_id_fighters_id_fk",
          "tableFrom": "draft_queues",
          "tableTo": "fighters",
          "columnsFrom": [
            "fighter_id"
          ],
          "columnsTo": [
            "id"
          ],
          "onDelete": "no action",
          "onUpdate": "no action"
        }
      },
      "compositePrimaryKeys": {},
      "uniqueConstraints": {
        "draft_queues_membership_id_fighter_id_unique": {
          "name": "draft_queues_membership_id_fighter_id_unique",
          "nullsNotDistinct": false,
          "columns": [
            "membership_id",
            "fighter_id"
          ]
        }
      },
      "policies": {},
      "checkConstraints": {},
      "isRLSEnabled": false
    },
    "public.drafts": {
      "name": "drafts",
      "schema": "",
      "columns": {
        "id": {
          "name": "id",
          "type": "text",
          "primaryKey": true,
          "notNull": true,
          "default": "'gen_random_uuid()'"
        },
        "league_id": {
          "name": "league_id",
          "type": "text",
          "primaryKey": false,
          "notNull": true
        },
        "type": {
          "name": "type",
          "type": "text",
          "primaryKey": false,
          "notNull": true,
          "default": "'snake'"
        },
        "status": {
          "name": "status",
          "type": "draft_status",
          "typeSchema": "public",
          "primaryKey": false,
          "notNull": true,
          "default": "'scheduled'"
        },
        "scheduled_start": {
          "name": "scheduled_start",
          "type": "timestamp with time zone",
          "primaryKey": false,
          "notNull": false
        },
        "pick_timer_seconds": {
          "name": "pick_timer_seconds",
          "type": "integer",
          "primaryKey": false,
          "notNull": true,
          "default": 60
        },
        "current_pick_number": {
          "name": "current_pick_number",
          "type": "integer",
          "primaryKey": false,
          "notNull": true,
          "default": 0
        },
        "draft_order": {
          "name": "draft_order",
          "type": "jsonb",
          "primaryKey": false,
          "notNull": true,
          "default": "'[]'::jsonb"
        },
        "clock_expires_at": {
          "name": "clock_expires_at",
          "type": "timestamp with time zone",
          "primaryKey": false,
          "notNull": false
        }
      },
      "indexes": {},
      "foreignKeys": {
        "drafts_league_id_leagues_id_fk": {
          "name": "drafts_league_id_leagues_id_fk",
          "tableFrom": "drafts",
          "tableTo": "leagues",
          "columnsFrom": [
            "league_id"
          ],
          "columnsTo": [
            "id"
          ],
          "onDelete": "no action",
          "onUpdate": "no action"
        }
      },
      "compositePrimaryKeys": {},
      "uniqueConstraints": {
        "drafts_league_id_unique": {
          "name": "drafts_league_id_unique",
          "nullsNotDistinct": false,
          "columns": [
            "league_id"
          ]
        }
      },
      "policies": {},
      "checkConstraints": {},
      "isRLSEnabled": false
    },
    "public.events": {
      "name": "events",
      "schema": "",
      "columns": {
        "id": {
          "name": "id",
          "type": "text",
          "primaryKey": true,
          "notNull": true,
          "default": "'gen_random_uuid()'"
        },
        "external_id": {
          "name": "external_id",
          "type": "text",
          "primaryKey": false,
          "notNull": true
        },
        "name": {
          "name": "name",
          "type": "text",
          "primaryKey": false,
          "notNull": true
        },
        "event_date": {
          "name": "event_date",
          "type": "timestamp with time zone",
          "primaryKey": false,
          "notNull": true
        },
        "location": {
          "name": "location",
          "type": "text",
          "primaryKey": false,
          "notNull": false
        },
        "lock_time": {
          "name": "lock_time",
          "type": "timestamp with time zone",
          "primaryKey": false,
          "notNull": true
        },
        "status": {
          "name": "status",
          "type": "event_status",
          "typeSchema": "public",
          "primaryKey": false,
          "notNull": true,
          "default": "'scheduled'"
        },
        "updated_at": {
          "name": "updated_at",
          "type": "timestamp with time zone",
          "primaryKey": false,
          "notNull": true,
          "default": "now()"
        }
      },
      "indexes": {},
      "foreignKeys": {},
      "compositePrimaryKeys": {},
      "uniqueConstraints": {
        "events_external_id_unique": {
          "name": "events_external_id_unique",
          "nullsNotDistinct": false,
          "columns": [
            "external_id"
          ]
        }
      },
      "policies": {},
      "checkConstraints": {},
      "isRLSEnabled": false
    },
    "public.fighters": {
      "name": "fighters",
      "schema": "",
      "columns": {
        "id": {
          "name": "id",
          "type": "text",
          "primaryKey": true,
          "notNull": true,
          "default": "'gen_random_uuid()'"
        },
        "external_id": {
          "name": "external_id",
          "type": "text",
          "primaryKey": false,
          "notNull": true
        },
        "name": {
          "name": "name",
          "type": "text",
          "primaryKey": false,
          "notNull": true
        },
        "nickname": {
          "name": "nickname",
          "type": "text",
          "primaryKey": false,
          "notNull": false
        },
        "weight_class": {
          "name": "weight_class",
          "type": "weight_class",
          "typeSchema": "public",
          "primaryKey": false,
          "notNull": true
        },
        "gender": {
          "name": "gender",
          "type": "text",
          "primaryKey": false,
          "notNull": true,
          "default": "'male'"
        },
        "photo_url": {
          "name": "photo_url",
          "type": "text",
          "primaryKey": false,
          "notNull": false
        },
        "record_w": {
          "name": "record_w",
          "type": "integer",
          "primaryKey": false,
          "notNull": true,
          "default": 0
        },
        "record_l": {
          "name": "record_l",
          "type": "integer",
          "primaryKey": false,
          "notNull": true,
          "default": 0
        },
        "record_d": {
          "name": "record_d",
          "type": "integer",
          "primaryKey": false,
          "notNull": true,
          "default": 0
        },
        "current_ranking": {
          "name": "current_ranking",
          "type": "integer",
          "primaryKey": false,
          "notNull": false
        },
        "is_champion": {
          "name": "is_champion",
          "type": "boolean",
          "primaryKey": false,
          "notNull": true,
          "default": false
        },
        "ranking_division": {
          "name": "ranking_division",
          "type": "weight_class",
          "typeSchema": "public",
          "primaryKey": false,
          "notNull": false
        },
        "status": {
          "name": "status",
          "type": "fighter_status",
          "typeSchema": "public",
          "primaryKey": false,
          "notNull": true,
          "default": "'active'"
        },
        "height_in": {
          "name": "height_in",
          "type": "real",
          "primaryKey": false,
          "notNull": false
        },
        "reach_in": {
          "name": "reach_in",
          "type": "real",
          "primaryKey": false,
          "notNull": false
        },
        "weight_lbs": {
          "name": "weight_lbs",
          "type": "real",
          "primaryKey": false,
          "notNull": false
        },
        "stance": {
          "name": "stance",
          "type": "text",
          "primaryKey": false,
          "notNull": false
        },
        "dob": {
          "name": "dob",
          "type": "date",
          "primaryKey": false,
          "notNull": false
        },
        "slpm": {
          "name": "slpm",
          "type": "real",
          "primaryKey": false,
          "notNull": false
        },
        "sapm": {
          "name": "sapm",
          "type": "real",
          "primaryKey": false,
          "notNull": false
        },
        "str_acc": {
          "name": "str_acc",
          "type": "real",
          "primaryKey": false,
          "notNull": false
        },
        "str_def": {
          "name": "str_def",
          "type": "real",
          "primaryKey": false,
          "notNull": false
        },
        "td_avg": {
          "name": "td_avg",
          "type": "real",
          "primaryKey": false,
          "notNull": false
        },
        "td_acc": {
          "name": "td_acc",
          "type": "real",
          "primaryKey": false,
          "notNull": false
        },
        "td_def": {
          "name": "td_def",
          "type": "real",
          "primaryKey": false,
          "notNull": false
        },
        "sub_avg": {
          "name": "sub_avg",
          "type": "real",
          "primaryKey": false,
          "notNull": false
        },
        "photo_license": {
          "name": "photo_license",
          "type": "text",
          "primaryKey": false,
          "notNull": false
        },
        "photo_attribution": {
          "name": "photo_attribution",
          "type": "text",
          "primaryKey": false,
          "notNull": false
        },
        "photo_source": {
          "name": "photo_source",
          "type": "text",
          "primaryKey": false,
          "notNull": false
        },
        "draft_score": {
          "name": "draft_score",
          "type": "real",
          "primaryKey": false,
          "notNull": false
        },
        "last_fight_at": {
          "name": "last_fight_at",
          "type": "date",
          "primaryKey": false,
          "notNull": false
        },
        "updated_at": {
          "name": "updated_at",
          "type": "timestamp with time zone",
          "primaryKey": false,
          "notNull": true,
          "default": "now()"
        }
      },
      "indexes": {},
      "foreignKeys": {},
      "compositePrimaryKeys": {},
      "uniqueConstraints": {
        "fighters_external_id_unique": {
          "name": "fighters_external_id_unique",
          "nullsNotDistinct": false,
          "columns": [
            "external_id"
          ]
        }
      },
      "policies": {},
      "checkConstraints": {},
      "isRLSEnabled": false
    },
    "public.league_memberships": {
      "name": "league_memberships",
      "schema": "",
      "columns": {
        "id": {
          "name": "id",
          "type": "text",
          "primaryKey": true,
          "notNull": true,
          "default": "'gen_random_uuid()'"
        },
        "league_id": {
          "name": "league_id",
          "type": "text",
          "primaryKey": false,
          "notNull": true
        },
        "user_id": {
          "name": "user_id",
          "type": "text",
          "primaryKey": false,
          "notNull": true
        },
        "team_name": {
          "name": "team_name",
          "type": "text",
          "primaryKey": false,
          "notNull": true
        },
        "role": {
          "name": "role",
          "type": "member_role",
          "typeSchema": "public",
          "primaryKey": false,
          "notNull": true,
          "default": "'member'"
        },
        "joined_at": {
          "name": "joined_at",
          "type": "timestamp with time zone",
          "primaryKey": false,
          "notNull": true,
          "default": "now()"
        },
        "fought_drop_used": {
          "name": "fought_drop_used",
          "type": "boolean",
          "primaryKey": false,
          "notNull": true,
          "default": false
        },
        "autodraft_enabled": {
          "name": "autodraft_enabled",
          "type": "boolean",
          "primaryKey": false,
          "notNull": true,
          "default": false
        }
      },
      "indexes": {},
      "foreignKeys": {
        "league_memberships_league_id_leagues_id_fk": {
          "name": "league_memberships_league_id_leagues_id_fk",
          "tableFrom": "league_memberships",
          "tableTo": "leagues",
          "columnsFrom": [
            "league_id"
          ],
          "columnsTo": [
            "id"
          ],
          "onDelete": "no action",
          "onUpdate": "no action"
        },
        "league_memberships_user_id_profiles_id_fk": {
          "name": "league_memberships_user_id_profiles_id_fk",
          "tableFrom": "league_memberships",
          "tableTo": "profiles",
          "columnsFrom": [
            "user_id"
          ],
          "columnsTo": [
            "id"
          ],
          "onDelete": "no action",
          "onUpdate": "no action"
        }
      },
      "compositePrimaryKeys": {},
      "uniqueConstraints": {
        "league_memberships_league_id_user_id_unique": {
          "name": "league_memberships_league_id_user_id_unique",
          "nullsNotDistinct": false,
          "columns": [
            "league_id",
            "user_id"
          ]
        }
      },
      "policies": {},
      "checkConstraints": {},
      "isRLSEnabled": false
    },
    "public.leagues": {
      "name": "leagues",
      "schema": "",
      "columns": {
        "id": {
          "name": "id",
          "type": "text",
          "primaryKey": true,
          "notNull": true,
          "default": "'gen_random_uuid()'"
        },
        "name": {
          "name": "name",
          "type": "text",
          "primaryKey": false,
          "notNull": true
        },
        "logo_url": {
          "name": "logo_url",
          "type": "text",
          "primaryKey": false,
          "notNull": false
        },
        "commissioner_id": {
          "name": "commissioner_id",
          "type": "text",
          "primaryKey": false,
          "notNull": true
        },
        "is_public": {
          "name": "is_public",
          "type": "boolean",
          "primaryKey": false,
          "notNull": true,
          "default": false
        },
        "invite_code": {
          "name": "invite_code",
          "type": "text",
          "primaryKey": false,
          "notNull": true
        },
        "season_start_date": {
          "name": "season_start_date",
          "type": "date",
          "primaryKey": false,
          "notNull": true
        },
        "season_end_event_id": {
          "name": "season_end_event_id",
          "type": "text",
          "primaryKey": false,
          "notNull": false
        },
        "status": {
          "name": "status",
          "type": "league_status",
          "typeSchema": "public",
          "primaryKey": false,
          "notNull": true,
          "default": "'setup'"
        },
        "created_at": {
          "name": "created_at",
          "type": "timestamp with time zone",
          "primaryKey": false,
          "notNull": true,
          "default": "now()"
        }
      },
      "indexes": {},
      "foreignKeys": {
        "leagues_commissioner_id_profiles_id_fk": {
          "name": "leagues_commissioner_id_profiles_id_fk",
          "tableFrom": "leagues",
          "tableTo": "profiles",
          "columnsFrom": [
            "commissioner_id"
          ],
          "columnsTo": [
            "id"
          ],
          "onDelete": "no action",
          "onUpdate": "no action"
        },
        "leagues_season_end_event_id_events_id_fk": {
          "name": "leagues_season_end_event_id_events_id_fk",
          "tableFrom": "leagues",
          "tableTo": "events",
          "columnsFrom": [
            "season_end_event_id"
          ],
          "columnsTo": [
            "id"
          ],
          "onDelete": "no action",
          "onUpdate": "no action"
        }
      },
      "compositePrimaryKeys": {},
      "uniqueConstraints": {
        "leagues_invite_code_unique": {
          "name": "leagues_invite_code_unique",
          "nullsNotDistinct": false,
          "columns": [
            "invite_code"
          ]
        }
      },
      "policies": {},
      "checkConstraints": {},
      "isRLSEnabled": false
    },
    "public.notifications": {
      "name": "notifications",
      "schema": "",
      "columns": {
        "id": {
          "name": "id",
          "type": "text",
          "primaryKey": true,
          "notNull": true,
          "default": "'gen_random_uuid()'"
        },
        "user_id": {
          "name": "user_id",
          "type": "text",
          "primaryKey": false,
          "notNull": true
        },
        "type": {
          "name": "type",
          "type": "notification_type",
          "typeSchema": "public",
          "primaryKey": false,
          "notNull": true
        },
        "payload": {
          "name": "payload",
          "type": "jsonb",
          "primaryKey": false,
          "notNull": true,
          "default": "'{}'::jsonb"
        },
        "read_at": {
          "name": "read_at",
          "type": "timestamp with time zone",
          "primaryKey": false,
          "notNull": false
        },
        "created_at": {
          "name": "created_at",
          "type": "timestamp with time zone",
          "primaryKey": false,
          "notNull": true,
          "default": "now()"
        }
      },
      "indexes": {},
      "foreignKeys": {
        "notifications_user_id_profiles_id_fk": {
          "name": "notifications_user_id_profiles_id_fk",
          "tableFrom": "notifications",
          "tableTo": "profiles",
          "columnsFrom": [
            "user_id"
          ],
          "columnsTo": [
            "id"
          ],
          "onDelete": "no action",
          "onUpdate": "no action"
        }
      },
      "compositePrimaryKeys": {},
      "uniqueConstraints": {},
      "policies": {},
      "checkConstraints": {},
      "isRLSEnabled": false
    },
    "public.profiles": {
      "name": "profiles",
      "schema": "",
      "columns": {
        "id": {
          "name": "id",
          "type": "text",
          "primaryKey": true,
          "notNull": true
        },
        "display_name": {
          "name": "display_name",
          "type": "text",
          "primaryKey": false,
          "notNull": true
        },
        "avatar_url": {
          "name": "avatar_url",
          "type": "text",
          "primaryKey": false,
          "notNull": false
        },
        "timezone": {
          "name": "timezone",
          "type": "text",
          "primaryKey": false,
          "notNull": true,
          "default": "'America/New_York'"
        },
        "created_at": {
          "name": "created_at",
          "type": "timestamp with time zone",
          "primaryKey": false,
          "notNull": true,
          "default": "now()"
        }
      },
      "indexes": {},
      "foreignKeys": {},
      "compositePrimaryKeys": {},
      "uniqueConstraints": {},
      "policies": {},
      "checkConstraints": {},
      "isRLSEnabled": false
    },
    "public.push_subscriptions": {
      "name": "push_subscriptions",
      "schema": "",
      "columns": {
        "id": {
          "name": "id",
          "type": "text",
          "primaryKey": true,
          "notNull": true,
          "default": "'gen_random_uuid()'"
        },
        "user_id": {
          "name": "user_id",
          "type": "text",
          "primaryKey": false,
          "notNull": true
        },
        "endpoint": {
          "name": "endpoint",
          "type": "text",
          "primaryKey": false,
          "notNull": true
        },
        "p256dh": {
          "name": "p256dh",
          "type": "text",
          "primaryKey": false,
          "notNull": true
        },
        "auth": {
          "name": "auth",
          "type": "text",
          "primaryKey": false,
          "notNull": true
        },
        "created_at": {
          "name": "created_at",
          "type": "timestamp with time zone",
          "primaryKey": false,
          "notNull": true,
          "default": "now()"
        }
      },
      "indexes": {},
      "foreignKeys": {
        "push_subscriptions_user_id_profiles_id_fk": {
          "name": "push_subscriptions_user_id_profiles_id_fk",
          "tableFrom": "push_subscriptions",
          "tableTo": "profiles",
          "columnsFrom": [
            "user_id"
          ],
          "columnsTo": [
            "id"
          ],
          "onDelete": "no action",
          "onUpdate": "no action"
        }
      },
      "compositePrimaryKeys": {},
      "uniqueConstraints": {
        "push_subscriptions_endpoint_unique": {
          "name": "push_subscriptions_endpoint_unique",
          "nullsNotDistinct": false,
          "columns": [
            "endpoint"
          ]
        }
      },
      "policies": {},
      "checkConstraints": {},
      "isRLSEnabled": false
    },
    "public.rosters": {
      "name": "rosters",
      "schema": "",
      "columns": {
        "id": {
          "name": "id",
          "type": "text",
          "primaryKey": true,
          "notNull": true,
          "default": "'gen_random_uuid()'"
        },
        "membership_id": {
          "name": "membership_id",
          "type": "text",
          "primaryKey": false,
          "notNull": true
        },
        "league_id": {
          "name": "league_id",
          "type": "text",
          "primaryKey": false,
          "notNull": true
        },
        "fighter_id": {
          "name": "fighter_id",
          "type": "text",
          "primaryKey": false,
          "notNull": true
        },
        "slot": {
          "name": "slot",
          "type": "slot",
          "typeSchema": "public",
          "primaryKey": false,
          "notNull": true
        },
        "acquired_at": {
          "name": "acquired_at",
          "type": "timestamp with time zone",
          "primaryKey": false,
          "notNull": true,
          "default": "now()"
        },
        "acquired_via": {
          "name": "acquired_via",
          "type": "acquired_via",
          "typeSchema": "public",
          "primaryKey": false,
          "notNull": true,
          "default": "'draft'"
        }
      },
      "indexes": {},
      "foreignKeys": {
        "rosters_membership_id_league_memberships_id_fk": {
          "name": "rosters_membership_id_league_memberships_id_fk",
          "tableFrom": "rosters",
          "tableTo": "league_memberships",
          "columnsFrom": [
            "membership_id"
          ],
          "columnsTo": [
            "id"
          ],
          "onDelete": "no action",
          "onUpdate": "no action"
        },
        "rosters_league_id_leagues_id_fk": {
          "name": "rosters_league_id_leagues_id_fk",
          "tableFrom": "rosters",
          "tableTo": "leagues",
          "columnsFrom": [
            "league_id"
          ],
          "columnsTo": [
            "id"
          ],
          "onDelete": "no action",
          "onUpdate": "no action"
        },
        "rosters_fighter_id_fighters_id_fk": {
          "name": "rosters_fighter_id_fighters_id_fk",
          "tableFrom": "rosters",
          "tableTo": "fighters",
          "columnsFrom": [
            "fighter_id"
          ],
          "columnsTo": [
            "id"
          ],
          "onDelete": "no action",
          "onUpdate": "no action"
        }
      },
      "compositePrimaryKeys": {},
      "uniqueConstraints": {
        "rosters_membership_id_slot_unique": {
          "name": "rosters_membership_id_slot_unique",
          "nullsNotDistinct": false,
          "columns": [
            "membership_id",
            "slot"
          ]
        },
        "rosters_league_id_fighter_id_unique": {
          "name": "rosters_league_id_fighter_id_unique",
          "nullsNotDistinct": false,
          "columns": [
            "league_id",
            "fighter_id"
          ]
        }
      },
      "policies": {},
      "checkConstraints": {},
      "isRLSEnabled": false
    },
    "public.scores": {
      "name": "scores",
      "schema": "",
      "columns": {
        "id": {
          "name": "id",
          "type": "text",
          "primaryKey": true,
          "notNull": true,
          "default": "'gen_random_uuid()'"
        },
        "membership_id": {
          "name": "membership_id",
          "type": "text",
          "primaryKey": false,
          "notNull": true
        },
        "bout_id": {
          "name": "bout_id",
          "type": "text",
          "primaryKey": false,
          "notNull": true
        },
        "fighter_id": {
          "name": "fighter_id",
          "type": "text",
          "primaryKey": false,
          "notNull": true
        },
        "points": {
          "name": "points",
          "type": "integer",
          "primaryKey": false,
          "notNull": true,
          "default": 0
        },
        "breakdown": {
          "name": "breakdown",
          "type": "jsonb",
          "primaryKey": false,
          "notNull": true,
          "default": "'{}'::jsonb"
        }
      },
      "indexes": {},
      "foreignKeys": {
        "scores_membership_id_league_memberships_id_fk": {
          "name": "scores_membership_id_league_memberships_id_fk",
          "tableFrom": "scores",
          "tableTo": "league_memberships",
          "columnsFrom": [
            "membership_id"
          ],
          "columnsTo": [
            "id"
          ],
          "onDelete": "no action",
          "onUpdate": "no action"
        },
        "scores_bout_id_bouts_id_fk": {
          "name": "scores_bout_id_bouts_id_fk",
          "tableFrom": "scores",
          "tableTo": "bouts",
          "columnsFrom": [
            "bout_id"
          ],
          "columnsTo": [
            "id"
          ],
          "onDelete": "no action",
          "onUpdate": "no action"
        },
        "scores_fighter_id_fighters_id_fk": {
          "name": "scores_fighter_id_fighters_id_fk",
          "tableFrom": "scores",
          "tableTo": "fighters",
          "columnsFrom": [
            "fighter_id"
          ],
          "columnsTo": [
            "id"
          ],
          "onDelete": "no action",
          "onUpdate": "no action"
        }
      },
      "compositePrimaryKeys": {},
      "uniqueConstraints": {
        "scores_membership_id_bout_id_unique": {
          "name": "scores_membership_id_bout_id_unique",
          "nullsNotDistinct": false,
          "columns": [
            "membership_id",
            "bout_id"
          ]
        }
      },
      "policies": {},
      "checkConstraints": {},
      "isRLSEnabled": false
    },
    "public.transactions": {
      "name": "transactions",
      "schema": "",
      "columns": {
        "id": {
          "name": "id",
          "type": "text",
          "primaryKey": true,
          "notNull": true,
          "default": "'gen_random_uuid()'"
        },
        "league_id": {
          "name": "league_id",
          "type": "text",
          "primaryKey": false,
          "notNull": true
        },
        "membership_id": {
          "name": "membership_id",
          "type": "text",
          "primaryKey": false,
          "notNull": true
        },
        "type": {
          "name": "type",
          "type": "transaction_type",
          "typeSchema": "public",
          "primaryKey": false,
          "notNull": true
        },
        "fighter_id": {
          "name": "fighter_id",
          "type": "text",
          "primaryKey": false,
          "notNull": true
        },
        "slot": {
          "name": "slot",
          "type": "slot",
          "typeSchema": "public",
          "primaryKey": false,
          "notNull": true
        },
        "was_locked_fighter": {
          "name": "was_locked_fighter",
          "type": "boolean",
          "primaryKey": false,
          "notNull": true,
          "default": false
        },
        "created_at": {
          "name": "created_at",
          "type": "timestamp with time zone",
          "primaryKey": false,
          "notNull": true,
          "default": "now()"
        }
      },
      "indexes": {},
      "foreignKeys": {
        "transactions_league_id_leagues_id_fk": {
          "name": "transactions_league_id_leagues_id_fk",
          "tableFrom": "transactions",
          "tableTo": "leagues",
          "columnsFrom": [
            "league_id"
          ],
          "columnsTo": [
            "id"
          ],
          "onDelete": "no action",
          "onUpdate": "no action"
        },
        "transactions_membership_id_league_memberships_id_fk": {
          "name": "transactions_membership_id_league_memberships_id_fk",
          "tableFrom": "transactions",
          "tableTo": "league_memberships",
          "columnsFrom": [
            "membership_id"
          ],
          "columnsTo": [
            "id"
          ],
          "onDelete": "no action",
          "onUpdate": "no action"
        },
        "transactions_fighter_id_fighters_id_fk": {
          "name": "transactions_fighter_id_fighters_id_fk",
          "tableFrom": "transactions",
          "tableTo": "fighters",
          "columnsFrom": [
            "fighter_id"
          ],
          "columnsTo": [
            "id"
          ],
          "onDelete": "no action",
          "onUpdate": "no action"
        }
      },
      "compositePrimaryKeys": {},
      "uniqueConstraints": {},
      "policies": {},
      "checkConstraints": {},
      "isRLSEnabled": false
    }
  },
  "enums": {
    "public.acquired_via": {
      "name": "acquired_via",
      "schema": "public",
      "values": [
        "draft",
        "free_agent"
      ]
    },
    "public.bout_method": {
      "name": "bout_method",
      "schema": "public",
      "values": [
        "KO",
        "TKO",
        "SUB",
        "DEC",
        "DQ",
        "NC"
      ]
    },
    "public.bout_status": {
      "name": "bout_status",
      "schema": "public",
      "values": [
        "scheduled",
        "completed",
        "cancelled"
      ]
    },
    "public.card_segment": {
      "name": "card_segment",
      "schema": "public",
      "values": [
        "early_prelim",
        "prelim",
        "main"
      ]
    },
    "public.draft_status": {
      "name": "draft_status",
      "schema": "public",
      "values": [
        "scheduled",
        "in_progress",
        "paused",
        "completed"
      ]
    },
    "public.event_status": {
      "name": "event_status",
      "schema": "public",
      "values": [
        "scheduled",
        "in_progress",
        "completed"
      ]
    },
    "public.fighter_status": {
      "name": "fighter_status",
      "schema": "public",
      "values": [
        "active",
        "inactive",
        "retired"
      ]
    },
    "public.league_status": {
      "name": "league_status",
      "schema": "public",
      "values": [
        "setup",
        "drafting",
        "active",
        "completed"
      ]
    },
    "public.member_role": {
      "name": "member_role",
      "schema": "public",
      "values": [
        "commissioner",
        "member"
      ]
    },
    "public.notification_type": {
      "name": "notification_type",
      "schema": "public",
      "values": [
        "draft_starting",
        "lock_reminder",
        "results_posted",
        "pick_on_clock",
        "league_invite"
      ]
    },
    "public.slot": {
      "name": "slot",
      "schema": "public",
      "values": [
        "FLW",
        "BW",
        "FW",
        "LW",
        "WW",
        "MW",
        "LHW",
        "HW",
        "WILDCARD"
      ]
    },
    "public.transaction_type": {
      "name": "transaction_type",
      "schema": "public",
      "values": [
        "draft_pick",
        "add",
        "drop"
      ]
    },
    "public.weight_class": {
      "name": "weight_class",
      "schema": "public",
      "values": [
        "FLW",
        "BW",
        "FW",
        "LW",
        "WW",
        "MW",
        "LHW",
        "HW"
      ]
    }
  },
  "schemas": {},
  "sequences": {},
  "roles": {},
  "policies": {},
  "views": {},
  "_meta": {
    "columns": {},
    "schemas": {},
    "tables": {}
  }
}